ArtisanPrint/ColorPrint.py
ArtisanPrint/__init__.py
ArtisanPrint/custom_exceptions.py
ArtisanPrint-1.0.0.dist-info/LICENSE
ArtisanPrint-1.0.0.dist-info/METADATA
ArtisanPrint-1.0.0.dist-info/WHEEL
ArtisanPrint-1.0.0.dist-info/top_level.txt
ArtisanPrint-1.0.0.dist-info/RECORD
