Metadata-Version: 2.1
Name: ArtisanPrint
Version: 1.0.0
Summary: A Python library for customizable text printing in the terminal.
Home-page: https://github.com/Naman-0206/ArtisanPrint
Author: Naman Garg
Author-email: edu.ngarg@gmail.com
License: MIT
Project-URL: Bug Tracker, https://github.com/Naman-0206/ArtisanPrint/issues
Keywords: text,printing,colors,styles,terminal,formatting,ANSI,console,output,CLI,developer,tool,utility,Python,library,package,customization,enhancement,programming,development
Classifier: Programming Language :: Python :: 3
Classifier: License :: OSI Approved :: MIT License
Classifier: Operating System :: OS Independent
Requires-Python: >=3.6
License-File: LICENSE
